README.txt
setup.cfg
setup.py
docs/HISTORY.txt
docs/INSTALL.txt
docs/LICENSE.GPL
docs/LICENSE.txt
my315ok/__init__.py
my315ok/__init__.pyc
my315ok.portlet.footer.egg-info/PKG-INFO
my315ok.portlet.footer.egg-info/SOURCES.txt
my315ok.portlet.footer.egg-info/dependency_links.txt
my315ok.portlet.footer.egg-info/entry_points.txt
my315ok.portlet.footer.egg-info/namespace_packages.txt
my315ok.portlet.footer.egg-info/not-zip-safe
my315ok.portlet.footer.egg-info/paster_plugins.txt
my315ok.portlet.footer.egg-info/requires.txt
my315ok.portlet.footer.egg-info/top_level.txt
my315ok/portlet/__init__.py
my315ok/portlet/__init__.pyc
my315ok/portlet/footer/__init__.py
my315ok/portlet/footer/__init__.pyc
my315ok/portlet/footer/configure.zcml
my315ok/portlet/footer/footerportlet.pt
my315ok/portlet/footer/footerportlet.py
my315ok/portlet/footer/footerportlet.pyc
my315ok/portlet/footer/static.pt
my315ok/portlet/footer/static.py
my315ok/portlet/footer/version.txt
my315ok/portlet/footer/profiles/default/metadata.xml
my315ok/portlet/footer/profiles/default/portlets.xml
my315ok/portlet/footer/tests/__init__.py
my315ok/portlet/footer/tests/base.py
my315ok/portlet/footer/tests/test_portlet.py