Metadata-Version: 1.0
Name: my315ok.portlet.footer
Version: 1.0dev-r332
Summary: a edited footer portlet
Home-page: http://315ok.org
Author: adam tang
Author-email: yuejun.tang@gmail.com
License: GPL
Keywords: footer portlet
Platform: UNKNOWN
Classifier: Framework :: Plone
Classifier: Programming Language :: Python
Classifier: Topic :: Software Development :: Libraries :: Python Modules
